LICENSE
MANIFEST.in
README.md
VERSION
setup.py
panther_utils/__init__.py
panther_utils/match_filters.py
panther_utils/network_filters.py
panther_utils/py.typed
panther_utils/standard_tags.py
panther_utils.egg-info/PKG-INFO
panther_utils.egg-info/SOURCES.txt
panther_utils.egg-info/dependency_links.txt
panther_utils.egg-info/requires.txt
panther_utils.egg-info/top_level.txt
tests/__init__.py
tests/test_match_filters.py
tests/test_network_filters.py