Metadata-Version: 2.1
Name: panther-utils
Version: 0.0.4
Summary: UNKNOWN
Home-page: https://panther.com
Author: Panther Labs Inc.
Author-email: support@panther.io
License: UNKNOWN
Keywords: security detection
Platform: UNKNOWN
Classifier: Development Status :: 1 - Planning
Classifier: License :: OSI Approved :: GNU Affero General Public License v3
Classifier: Environment :: Console
Classifier: Intended Audience :: Developers
Classifier: Topic :: Security
Classifier: Typing :: Typed
Classifier: Programming Language :: Python :: 3
Requires-Python: >=3.9
License-File: LICENSE
